aether/__init__.py
aether/base.py
aether/errors.py
aether/safe_string.py
aether/utils.py
aether/plugins/__init__.py
aether/plugins/alpinejs/__init__.py
aether/plugins/chartjs/__init__.py
aether/plugins/htmx/__init__.py
aether/plugins/htmx/_base.py
aether/plugins/tailwindcss/__init__.py
aether/plugins/tailwindcss/utils.py
aether/tags/__init__.py
aether/tags/html/__init__.py
aether/tags/html/_base.py
aether/tags/html/a.py
aether/tags/html/abbr.py
aether/tags/html/address.py
aether/tags/html/area.py
aether/tags/html/article.py
aether/tags/html/aside.py
aether/tags/html/audio.py
aether/tags/html/b.py
aether/tags/html/base.py
aether/tags/html/bdi.py
aether/tags/html/bdo.py
aether/tags/html/blockquote.py
aether/tags/html/body.py
aether/tags/html/br.py
aether/tags/html/button.py
aether/tags/html/canvas.py
aether/tags/html/caption.py
aether/tags/html/cite.py
aether/tags/html/code.py
aether/tags/html/col.py
aether/tags/html/colgroup.py
aether/tags/html/data.py
aether/tags/html/datalist.py
aether/tags/html/dd.py
aether/tags/html/del_.py
aether/tags/html/details.py
aether/tags/html/dfn.py
aether/tags/html/dialog.py
aether/tags/html/div.py
aether/tags/html/dl.py
aether/tags/html/dt.py
aether/tags/html/em.py
aether/tags/html/embed.py
aether/tags/html/fieldset.py
aether/tags/html/figcaption.py
aether/tags/html/figure.py
aether/tags/html/footer.py
aether/tags/html/form.py
aether/tags/html/h.py
aether/tags/html/head.py
aether/tags/html/header.py
aether/tags/html/hgroup.py
aether/tags/html/hr.py
aether/tags/html/html.py
aether/tags/html/i.py
aether/tags/html/iframe.py
aether/tags/html/img.py
aether/tags/html/input.py
aether/tags/html/ins.py
aether/tags/html/kbd.py
aether/tags/html/label.py
aether/tags/html/legend.py
aether/tags/html/li.py
aether/tags/html/link.py
aether/tags/html/main.py
aether/tags/html/map.py
aether/tags/html/mark.py
aether/tags/html/menu.py
aether/tags/html/meta.py
aether/tags/html/meter.py
aether/tags/html/nav.py
aether/tags/html/noscript.py
pyaether-0.4.17.dist-info/METADATA
pyaether-0.4.17.dist-info/WHEEL
pyaether-0.4.17.dist-info/RECORD
