Metadata-Version: 2.4
Name: pyaether
Version: 0.4.17
Summary: DSL for writing HTML user interfaces in Python.
Project-URL: homepage, https://github.com/pyaether/aether
Project-URL: repository, https://github.com/pyaether/aether
Project-URL: documentation, https://github.com/pyaether/aether
Author-email: Saurabh Ghanekar <ghanekarsaurabh8@gmail.com>
License-Expression: BSD-2-Clause
Classifier: Operating System :: OS Independent
Classifier: Programming Language :: Python :: 3
Requires-Python: >=3.10
Requires-Dist: pydantic>=2.10
Requires-Dist: typing-extensions>=4
